uwkm_streamfields/__init__.py
uwkm_streamfields/blocks.py
uwkm_streamfields/icons.py
uwkm_streamfields/models.py
uwkm_streamfields/widgets.py
uwkm_streamfields/settings/base.py
uwkm_streamfields/static/.DS_Store
uwkm_streamfields/static/assets/loader.gif
uwkm_streamfields/static/colorpicker/.DS_Store
uwkm_streamfields/static/colorpicker/css/colorpicker.css
uwkm_streamfields/static/colorpicker/css/layout.css
uwkm_streamfields/static/colorpicker/images/Thumbs.db
uwkm_streamfields/static/colorpicker/images/blank.gif
uwkm_streamfields/static/colorpicker/images/colorpicker_background.png
uwkm_streamfields/static/colorpicker/images/colorpicker_hex.png
uwkm_streamfields/static/colorpicker/images/colorpicker_hsb_b.png
uwkm_streamfields/static/colorpicker/images/colorpicker_hsb_h.png
uwkm_streamfields/static/colorpicker/images/colorpicker_hsb_s.png
uwkm_streamfields/static/colorpicker/images/colorpicker_indic.gif
uwkm_streamfields/static/colorpicker/images/colorpicker_overlay.png
uwkm_streamfields/static/colorpicker/images/colorpicker_rgb_b.png
uwkm_streamfields/static/colorpicker/images/colorpicker_rgb_g.png
uwkm_streamfields/static/colorpicker/images/colorpicker_rgb_r.png
uwkm_streamfields/static/colorpicker/images/colorpicker_select.gif
uwkm_streamfields/static/colorpicker/images/colorpicker_submit.png
uwkm_streamfields/static/colorpicker/images/custom_background.png
uwkm_streamfields/static/colorpicker/images/custom_hex.png
uwkm_streamfields/static/colorpicker/images/custom_hsb_b.png
uwkm_streamfields/static/colorpicker/images/custom_hsb_h.png
uwkm_streamfields/static/colorpicker/images/custom_hsb_s.png
uwkm_streamfields/static/colorpicker/images/custom_indic.gif
uwkm_streamfields/static/colorpicker/images/custom_rgb_b.png
uwkm_streamfields/static/colorpicker/images/custom_rgb_g.png
uwkm_streamfields/static/colorpicker/images/custom_rgb_r.png
uwkm_streamfields/static/colorpicker/images/custom_submit.png
uwkm_streamfields-1.4.0.dist-info/DESCRIPTION.rst
uwkm_streamfields-1.4.0.dist-info/METADATA
uwkm_streamfields-1.4.0.dist-info/RECORD
uwkm_streamfields-1.4.0.dist-info/WHEEL
uwkm_streamfields-1.4.0.dist-info/metadata.json
uwkm_streamfields-1.4.0.dist-info/top_level.txt
