Metadata-Version: 2.0
Name: uwkm-streamfields
Version: 1.4.0
Summary: Wagtail Bootstrap Streamfields
Home-page: https://github.com/UWKM/uwkm_streamfields/
Author: UWKM
Author-email: support@uwkm.nl
License: MIT
Download-URL: https://github.com/UWKM/uwkm_streamfields/archive/master.zip
Keywords: wagtail cms streamfields bootstrap uwkm
Platform: UNKNOWN
Provides-Extra: dev
Provides-Extra: test
